<?xml version="1.0" encoding="System"?>
<icondef>
  <name>D83CDFFC (Small)</name>
  <creation>2015-10-17</creation>
  <version>1.0</version>
  <description>vKontakte skin colored emoji set D83CDFFC (Small)</description>
  <home>www.eyecu.ru</home>
  <author>Yagiza</author>
  <icon>
    <text>&#xD83D;&#xDC4D;</text>
    <object mime="image/png">D83DDC4D.png</object>
  </icon>
  <icon>
    <text>&#xD83D;&#xDC4E;</text>
    <object mime="image/png">D83DDC4E.png</object>
  </icon>
  <icon>
    <text>&#x261D;</text>
    <object mime="image/png">261D.png</object>
  </icon>
  <icon>
    <text>&#x270C;</text>
    <object mime="image/png">270C.png</object>
  </icon>
  <icon>
    <text>&#xD83D;&#xDC4C;</text>
    <object mime="image/png">D83DDC4C.png</object>
  </icon>
  <icon>
    <text>&#xD83D;&#xDC4F;</text>
    <object mime="image/png">D83DDC4F.png</object>
  </icon>
  <icon>
    <text>&#xD83D;&#xDC4A;</text>
    <object mime="image/png">D83DDC4A.png</object>
  </icon>
  <icon>
    <text>&#x270B;</text>
    <object mime="image/png">270B.png</object>
  </icon>
  <icon>
    <text>&#xD83D;&#xDE4F;</text>
    <object mime="image/png">D83DDE4F.png</object>
  </icon>
  <icon>
    <text>&#xD83D;&#xDC43;</text>
    <object mime="image/png">D83DDC43.png</object>
  </icon>
  <icon>
    <text>&#xD83D;&#xDC46;</text>
    <object mime="image/png">D83DDC46.png</object>
  </icon>
  <icon>
    <text>&#xD83D;&#xDC47;</text>
    <object mime="image/png">D83DDC47.png</object>
  </icon>
  <icon>
    <text>&#xD83D;&#xDC48;</text>
    <object mime="image/png">D83DDC48.png</object>
  </icon>
  <icon>
    <text>&#xD83D;&#xDCAA;</text>
    <object mime="image/png">D83DDCAA.png</object>
  </icon>
  <icon>
    <text>&#xD83D;&#xDC42;</text>
    <object mime="image/png">D83DDC42.png</object>
  </icon>
  <icon>
    <text>&#xD83C;&#xDF85;</text>
    <object mime="image/png">D83CDF85.png</object>
  </icon>
  <icon>
    <text>&#x270A;</text>
    <object mime="image/png">270A.png</object>
  </icon>
  <icon>
    <text>&#xD83C;&#xDFC3;</text>
    <object mime="image/png">D83CDFC3.png</object>
  </icon>
  <icon>
    <text>&#xD83C;&#xDFC4;</text>
    <object mime="image/png">D83CDFC4.png</object>
  </icon>
  <icon>
    <text>&#xD83C;&#xDFC7;</text>
    <object mime="image/png">D83CDFC7.png</object>
  </icon>
  <icon>
    <text>&#xD83C;&#xDFCA;</text>
    <object mime="image/png">D83CDFCA.png</object>
  </icon>
  <icon>
    <text>&#xD83D;&#xDC4B;</text>
    <object mime="image/png">D83DDC4B.png</object>
  </icon>
  <icon>
    <text>&#xD83D;&#xDC50;</text>
    <object mime="image/png">D83DDC50.png</object>
  </icon>
  <icon>
    <text>&#xD83D;&#xDC66;</text>
    <object mime="image/png">D83DDC66.png</object>
  </icon>
  <icon>
    <text>&#xD83D;&#xDC67;</text>
    <object mime="image/png">D83DDC67.png</object>
  </icon>
  <icon>
    <text>&#xD83D;&#xDC68;</text>
    <object mime="image/png">D83DDC68.png</object>
  </icon>
  <icon>
    <text>&#xD83D;&#xDC69;</text>
    <object mime="image/png">D83DDC69.png</object>
  </icon>
  <icon>
    <text>&#xD83D;&#xDC6E;</text>
    <object mime="image/png">D83DDC6E.png</object>
  </icon>
  <icon>
    <text>&#xD83D;&#xDC70;</text>
    <object mime="image/png">D83DDC70.png</object>
  </icon>
  <icon>
    <text>&#xD83D;&#xDC71;</text>
    <object mime="image/png">D83DDC71.png</object>
  </icon>
  <icon>
    <text>&#xD83D;&#xDC72;</text>
    <object mime="image/png">D83DDC72.png</object>
  </icon>
  <icon>
    <text>&#xD83D;&#xDC73;</text>
    <object mime="image/png">D83DDC73.png</object>
  </icon>
  <icon>
    <text>&#xD83D;&#xDC74;</text>
    <object mime="image/png">D83DDC74.png</object>
  </icon>
  <icon>
    <text>&#xD83D;&#xDC75;</text>
    <object mime="image/png">D83DDC75.png</object>
  </icon>
  <icon>
    <text>&#xD83D;&#xDC76;</text>
    <object mime="image/png">D83DDC76.png</object>
  </icon>
  <icon>
    <text>&#xD83D;&#xDC77;</text>
    <object mime="image/png">D83DDC77.png</object>
  </icon>
  <icon>
    <text>&#xD83D;&#xDC78;</text>
    <object mime="image/png">D83DDC78.png</object>
  </icon>
  <icon>
    <text>&#xD83D;&#xDC7C;</text>
    <object mime="image/png">D83DDC7C.png</object>
  </icon>
  <icon>
    <text>&#xD83D;&#xDC81;</text>
    <object mime="image/png">D83DDC81.png</object>
  </icon>
  <icon>
    <text>&#xD83D;&#xDC82;</text>
    <object mime="image/png">D83DDC82.png</object>
  </icon>
  <icon>
    <text>&#xD83D;&#xDC83;</text>
    <object mime="image/png">D83DDC83.png</object>
  </icon>
  <icon>
    <text>&#xD83D;&#xDC85;</text>
    <object mime="image/png">D83DDC85.png</object>
  </icon>
  <icon>
    <text>&#xD83D;&#xDC86;</text>
    <object mime="image/png">D83DDC86.png</object>
  </icon>
  <icon>
    <text>&#xD83D;&#xDC87;</text>
    <object mime="image/png">D83DDC87.png</object>
  </icon>
  <icon>
    <text>&#xD83D;&#xDE45;</text>
    <object mime="image/png">D83DDE45.png</object>
  </icon>
  <icon>
    <text>&#xD83D;&#xDE46;</text>
    <object mime="image/png">D83DDE46.png</object>
  </icon>
  <icon>
    <text>&#xD83D;&#xDE47;</text>
    <object mime="image/png">D83DDE47.png</object>
  </icon>
  <icon>
    <text>&#xD83D;&#xDE4B;</text>
    <object mime="image/png">D83DDE4B.png</object>
  </icon>
  <icon>
    <text>&#xD83D;&#xDE4C;</text>
    <object mime="image/png">D83DDE4C.png</object>
  </icon>
  <icon>
    <text>&#xD83D;&#xDE4E;</text>
    <object mime="image/png">D83DDE4E.png</object>
  </icon>
  <icon>
    <text>&#xD83D;&#xDEA3;</text>
    <object mime="image/png">D83DDEA3.png</object>
  </icon>
  <icon>
    <text>&#xD83D;&#xDEB4;</text>
    <object mime="image/png">D83DDEB4.png</object>
  </icon>
  <icon>
    <text>&#xD83D;&#xDEB5;</text>
    <object mime="image/png">D83DDEB5.png</object>
  </icon>
  <icon>
    <text>&#xD83D;&#xDEB6;</text>
    <object mime="image/png">D83DDEB6.png</object>
  </icon>
  <icon>
    <text>&#xD83D;</text>
    <object mime="image/png">D83DDEC0.png</object>
  </icon>
  <icon>
    <text>&#xD83D;&#xDC49;</text>
    <object mime="image/png">D83DDC49.png</object>
  </icon>
</icondef>
