<?xml version="1.0" encoding="System"?>
<icondef>
  <icon>
    <text>&#xD83D;&#xDE4D;&#xD83C;&#xDFFB;</text>
    <object mime="image/png">D83DDE4DD83CDFFB_2x.png</object>
  </icon>
  <icon>
    <text>&#x270D;&#xD83C;&#xDFFB;</text>
    <object mime="image/png">270DD83CDFFB_2x.png</object>
  </icon>
  <icon>
    <text>&#xD83D;&#xDD90;&#xD83C;&#xDFFB;</text>
    <object mime="image/png">D83DDD90D83CDFFB_2x.png</object>
  </icon>
  <icon>
    <text>&#xD83D;&#xDD96;&#xD83C;&#xDFFB;</text>
    <object mime="image/png">D83DDD96D83CDFFB_2x.png</object>
  </icon>
</icondef>
